{
  "generated_at": "2026-06-01T19:07:34.432904+00:00",
  "as_of": "2026-06-01",
  "training_window_years": 3,
  "horizon_days": 30,
  "concentration_diagnostic": {
    "concentrated": false,
    "dominant_signal": "NEUTRE",
    "ratio": 0.2826,
    "n": 46,
    "threshold": 0.7
  },
  "liquidity_diagnostics": [
    {
      "ticker": "ABJC_ci",
      "illiquid_ratio": 0.177,
      "rows_raw": 3577,
      "rows_kept": 2944,
      "excluded": false
    },
    {
      "ticker": "BICB_bj",
      "illiquid_ratio": 0.0458,
      "rows_raw": 284,
      "rows_kept": 271,
      "excluded": false
    },
    {
      "ticker": "BICC_ci",
      "illiquid_ratio": 0.2475,
      "rows_raw": 3438,
      "rows_kept": 2587,
      "excluded": false
    },
    {
      "ticker": "BNBC_ci",
      "illiquid_ratio": 0.205,
      "rows_raw": 3064,
      "rows_kept": 2436,
      "excluded": false
    },
    {
      "ticker": "BOABF_bf",
      "illiquid_ratio": 0.1737,
      "rows_raw": 3465,
      "rows_kept": 2863,
      "excluded": false
    },
    {
      "ticker": "BOAB_bj",
      "illiquid_ratio": 0.3238,
      "rows_raw": 4077,
      "rows_kept": 2757,
      "excluded": false
    },
    {
      "ticker": "BOAC_ci",
      "illiquid_ratio": 0.1714,
      "rows_raw": 3559,
      "rows_kept": 2949,
      "excluded": false
    },
    {
      "ticker": "BOAM_ml",
      "illiquid_ratio": 0.1037,
      "rows_raw": 2546,
      "rows_kept": 2282,
      "excluded": false
    },
    {
      "ticker": "BOAN_ne",
      "illiquid_ratio": 0.2212,
      "rows_raw": 3946,
      "rows_kept": 3073,
      "excluded": false
    },
    {
      "ticker": "BOAS_sn",
      "illiquid_ratio": 0.123,
      "rows_raw": 2936,
      "rows_kept": 2575,
      "excluded": false
    },
    {
      "ticker": "CABC_ci",
      "illiquid_ratio": 0.2255,
      "rows_raw": 3153,
      "rows_kept": 2442,
      "excluded": false
    },
    {
      "ticker": "CBIBF_bf",
      "illiquid_ratio": 0.2467,
      "rows_raw": 2306,
      "rows_kept": 1737,
      "excluded": false
    },
    {
      "ticker": "CFAC_ci",
      "illiquid_ratio": 0.2201,
      "rows_raw": 3148,
      "rows_kept": 2455,
      "excluded": false
    },
    {
      "ticker": "CIEC_ci",
      "illiquid_ratio": 0.1783,
      "rows_raw": 4279,
      "rows_kept": 3516,
      "excluded": false
    },
    {
      "ticker": "ECOC_ci",
      "illiquid_ratio": 0.098,
      "rows_raw": 2173,
      "rows_kept": 1960,
      "excluded": false
    },
    {
      "ticker": "ETIT_tg",
      "illiquid_ratio": 0.6051,
      "rows_raw": 2970,
      "rows_kept": 1173,
      "excluded": true
    },
    {
      "ticker": "FTSC_ci",
      "illiquid_ratio": 0.1563,
      "rows_raw": 4147,
      "rows_kept": 3499,
      "excluded": false
    },
    {
      "ticker": "LNBB_bj",
      "illiquid_ratio": 0.1187,
      "rows_raw": 379,
      "rows_kept": 334,
      "excluded": false
    },
    {
      "ticker": "NEIC_ci",
      "illiquid_ratio": 0.2795,
      "rows_raw": 2290,
      "rows_kept": 1650,
      "excluded": false
    },
    {
      "ticker": "NSBC_ci",
      "illiquid_ratio": 0.119,
      "rows_raw": 2151,
      "rows_kept": 1895,
      "excluded": false
    },
    {
      "ticker": "NTLC_ci",
      "illiquid_ratio": 0.2663,
      "rows_raw": 3143,
      "rows_kept": 2306,
      "excluded": false
    },
    {
      "ticker": "ONTBF_bf",
      "illiquid_ratio": 0.1569,
      "rows_raw": 3933,
      "rows_kept": 3316,
      "excluded": false
    },
    {
      "ticker": "ORAC_ci",
      "illiquid_ratio": 0.0935,
      "rows_raw": 888,
      "rows_kept": 805,
      "excluded": false
    },
    {
      "ticker": "ORGT_tg",
      "illiquid_ratio": 0.209,
      "rows_raw": 1713,
      "rows_kept": 1355,
      "excluded": false
    },
    {
      "ticker": "PALC_ci",
      "illiquid_ratio": 0.0987,
      "rows_raw": 2876,
      "rows_kept": 2592,
      "excluded": false
    },
    {
      "ticker": "PRSC_ci",
      "illiquid_ratio": 0.2486,
      "rows_raw": 2156,
      "rows_kept": 1620,
      "excluded": false
    },
    {
      "ticker": "SAFC_ci",
      "illiquid_ratio": 0.2879,
      "rows_raw": 1358,
      "rows_kept": 967,
      "excluded": false
    },
    {
      "ticker": "SCRC_ci",
      "illiquid_ratio": 0.1326,
      "rows_raw": 2383,
      "rows_kept": 2067,
      "excluded": false
    },
    {
      "ticker": "SDCC_ci",
      "illiquid_ratio": 0.2203,
      "rows_raw": 3672,
      "rows_kept": 2863,
      "excluded": false
    },
    {
      "ticker": "SDSC_ci",
      "illiquid_ratio": 0.1938,
      "rows_raw": 3664,
      "rows_kept": 2954,
      "excluded": false
    },
    {
      "ticker": "SEMC_ci",
      "illiquid_ratio": 0.0093,
      "rows_raw": 108,
      "rows_kept": 107,
      "excluded": false
    },
    {
      "ticker": "SGBC_ci",
      "illiquid_ratio": 0.1575,
      "rows_raw": 4160,
      "rows_kept": 3505,
      "excluded": false
    },
    {
      "ticker": "SHEC_ci",
      "illiquid_ratio": 0.2119,
      "rows_raw": 3978,
      "rows_kept": 3135,
      "excluded": false
    },
    {
      "ticker": "SIBC_ci",
      "illiquid_ratio": 0.0912,
      "rows_raw": 2457,
      "rows_kept": 2233,
      "excluded": false
    },
    {
      "ticker": "SICC_ci",
      "illiquid_ratio": 0.2987,
      "rows_raw": 1617,
      "rows_kept": 1134,
      "excluded": false
    },
    {
      "ticker": "SIVC_ci",
      "illiquid_ratio": 0.2869,
      "rows_raw": 3754,
      "rows_kept": 2677,
      "excluded": false
    },
    {
      "ticker": "SLBC_ci",
      "illiquid_ratio": 0.3338,
      "rows_raw": 2385,
      "rows_kept": 1589,
      "excluded": false
    },
    {
      "ticker": "SMBC_ci",
      "illiquid_ratio": 0.2228,
      "rows_raw": 3133,
      "rows_kept": 2435,
      "excluded": false
    },
    {
      "ticker": "SNTS_sn",
      "illiquid_ratio": 0.2544,
      "rows_raw": 4639,
      "rows_kept": 3459,
      "excluded": false
    },
    {
      "ticker": "SOGC_ci",
      "illiquid_ratio": 0.1591,
      "rows_raw": 4118,
      "rows_kept": 3463,
      "excluded": false
    },
    {
      "ticker": "SPHC_ci",
      "illiquid_ratio": 0.1658,
      "rows_raw": 4282,
      "rows_kept": 3572,
      "excluded": false
    },
    {
      "ticker": "STAC_ci",
      "illiquid_ratio": 0.3026,
      "rows_raw": 2211,
      "rows_kept": 1542,
      "excluded": false
    },
    {
      "ticker": "STBC_ci",
      "illiquid_ratio": 0.2626,
      "rows_raw": 3286,
      "rows_kept": 2423,
      "excluded": false
    },
    {
      "ticker": "TTLC_ci",
      "illiquid_ratio": 0.1534,
      "rows_raw": 3657,
      "rows_kept": 3096,
      "excluded": false
    },
    {
      "ticker": "TTLS_sn",
      "illiquid_ratio": 0.1344,
      "rows_raw": 2738,
      "rows_kept": 2370,
      "excluded": false
    },
    {
      "ticker": "UNLC_ci",
      "illiquid_ratio": 0.3773,
      "rows_raw": 1752,
      "rows_kept": 1091,
      "excluded": false
    },
    {
      "ticker": "UNXC_ci",
      "illiquid_ratio": 0.1529,
      "rows_raw": 3375,
      "rows_kept": 2859,
      "excluded": false
    }
  ],
  "signals": {
    "ABJC_ci": {
      "ticker": "ABJC_ci",
      "last_price": 3210.0,
      "last_date": "2026-06-01",
      "signal": "ACHAT FORT",
      "confidence": "Haute",
      "target_30d": 3723.83,
      "trend": "UP",
      "yhat": 3723.83,
      "yhat_lower": 3541.06,
      "yhat_upper": 3905.89,
      "train_start": "2023-06-01",
      "train_end": "2026-06-01",
      "train_rows": 691,
      "train_annualized_return": 0.4096
    },
    "BICB_bj": {
      "ticker": "BICB_bj",
      "last_price": 5250.0,
      "last_date": "2026-06-01",
      "signal": "NEUTRE",
      "confidence": "Haute",
      "target_30d": 5278.47,
      "trend": "UP",
      "yhat": 5278.47,
      "yhat_lower": 5201.08,
      "yhat_upper": 5361.23,
      "train_start": "2025-04-28",
      "train_end": "2026-06-01",
      "train_rows": 271,
      "train_annualized_return": -0.0573
    },
    "BICC_ci": {
      "ticker": "BICC_ci",
      "last_price": 28300.0,
      "last_date": "2026-06-01",
      "signal": "NEUTRE",
      "confidence": "Haute",
      "target_30d": 28717.49,
      "trend": "UP",
      "yhat": 28717.49,
      "yhat_lower": 27840.74,
      "yhat_upper": 29627.46,
      "train_start": "2023-06-01",
      "train_end": "2026-06-01",
      "train_rows": 599,
      "train_annualized_return": 0.6158
    },
    "BNBC_ci": {
      "ticker": "BNBC_ci",
      "last_price": 1700.0,
      "last_date": "2026-06-01",
      "signal": "NEUTRE",
      "confidence": "Moyenne",
      "target_30d": 1685.42,
      "trend": "DOWN",
      "yhat": 1685.42,
      "yhat_lower": 1535.77,
      "yhat_upper": 1821.42,
      "train_start": "2023-06-01",
      "train_end": "2026-06-01",
      "train_rows": 695,
      "train_annualized_return": -0.043
    },
    "BOABF_bf": {
      "ticker": "BOABF_bf",
      "last_price": 5585.0,
      "last_date": "2026-06-01",
      "signal": "ACHAT",
      "confidence": "Haute",
      "target_30d": 5874.01,
      "trend": "UP",
      "yhat": 5874.01,
      "yhat_lower": 5690.44,
      "yhat_upper": 6056.61,
      "train_start": "2023-06-01",
      "train_end": "2026-06-01",
      "train_rows": 714,
      "train_annualized_return": 0.2665
    },
    "BOAB_bj": {
      "ticker": "BOAB_bj",
      "last_price": 8800.0,
      "last_date": "2026-06-01",
      "signal": "ACHAT",
      "confidence": "Haute",
      "target_30d": 9355.57,
      "trend": "UP",
      "yhat": 9355.57,
      "yhat_lower": 9103.42,
      "yhat_upper": 9579.48,
      "train_start": "2023-06-01",
      "train_end": "2026-06-01",
      "train_rows": 713,
      "train_annualized_return": 0.4557
    },
    "BOAC_ci": {
      "ticker": "BOAC_ci",
      "last_price": 8995.0,
      "last_date": "2026-06-01",
      "signal": "NEUTRE",
      "confidence": "Haute",
      "target_30d": 9063.82,
      "trend": "UP",
      "yhat": 9063.82,
      "yhat_lower": 8810.12,
      "yhat_upper": 9308.57,
      "train_start": "2023-06-01",
      "train_end": "2026-06-01",
      "train_rows": 734,
      "train_annualized_return": 0.5322
    },
    "BOAM_ml": {
      "ticker": "BOAM_ml",
      "last_price": 5245.0,
      "last_date": "2026-06-01",
      "signal": "VENTE",
      "confidence": "Haute",
      "target_30d": 5077.25,
      "trend": "DOWN",
      "yhat": 5077.25,
      "yhat_lower": 4939.24,
      "yhat_upper": 5217.73,
      "train_start": "2023-06-01",
      "train_end": "2026-06-01",
      "train_rows": 715,
      "train_annualized_return": 0.8356
    },
    "BOAN_ne": {
      "ticker": "BOAN_ne",
      "last_price": 3700.0,
      "last_date": "2026-06-01",
      "signal": "VENTE FORTE",
      "confidence": "Haute",
      "target_30d": 3245.79,
      "trend": "DOWN",
      "yhat": 3245.79,
      "yhat_lower": 3015.33,
      "yhat_upper": 3470.37,
      "train_start": "2023-06-01",
      "train_end": "2026-06-01",
      "train_rows": 729,
      "train_annualized_return": 0.0068
    },
    "BOAS_sn": {
      "ticker": "BOAS_sn",
      "last_price": 7565.0,
      "last_date": "2026-06-01",
      "signal": "ACHAT",
      "confidence": "Haute",
      "target_30d": 7839.16,
      "trend": "UP",
      "yhat": 7839.16,
      "yhat_lower": 7641.53,
      "yhat_upper": 8053.77,
      "train_start": "2023-06-01",
      "train_end": "2026-06-01",
      "train_rows": 693,
      "train_annualized_return": 0.6387
    },
    "CABC_ci": {
      "ticker": "CABC_ci",
      "last_price": 3465.0,
      "last_date": "2026-06-01",
      "signal": "ACHAT FORT",
      "confidence": "Haute",
      "target_30d": 4195.32,
      "trend": "UP",
      "yhat": 4195.32,
      "yhat_lower": 3983.95,
      "yhat_upper": 4408.92,
      "train_start": "2023-06-01",
      "train_end": "2026-06-01",
      "train_rows": 667,
      "train_annualized_return": 0.5101
    },
    "CBIBF_bf": {
      "ticker": "CBIBF_bf",
      "last_price": 21510.0,
      "last_date": "2026-06-01",
      "signal": "NEUTRE",
      "confidence": "Haute",
      "target_30d": 21767.35,
      "trend": "UP",
      "yhat": 21767.35,
      "yhat_lower": 21319.35,
      "yhat_upper": 22261.49,
      "train_start": "2023-06-01",
      "train_end": "2026-06-01",
      "train_rows": 678,
      "train_annualized_return": 0.4019
    },
    "CFAC_ci": {
      "ticker": "CFAC_ci",
      "last_price": 1505.0,
      "last_date": "2026-06-01",
      "signal": "ACHAT",
      "confidence": "Moyenne",
      "target_30d": 1574.25,
      "trend": "UP",
      "yhat": 1574.25,
      "yhat_lower": 1439.36,
      "yhat_upper": 1705.86,
      "train_start": "2023-06-01",
      "train_end": "2026-06-01",
      "train_rows": 680,
      "train_annualized_return": 0.25
    },
    "CIEC_ci": {
      "ticker": "CIEC_ci",
      "last_price": 4200.0,
      "last_date": "2026-06-01",
      "signal": "VENTE",
      "confidence": "Haute",
      "target_30d": 4010.57,
      "trend": "DOWN",
      "yhat": 4010.57,
      "yhat_lower": 3891.56,
      "yhat_upper": 4132.44,
      "train_start": "2023-06-01",
      "train_end": "2026-06-01",
      "train_rows": 685,
      "train_annualized_return": 0.2708
    },
    "ECOC_ci": {
      "ticker": "ECOC_ci",
      "last_price": 16250.0,
      "last_date": "2026-06-01",
      "signal": "ACHAT",
      "confidence": "Haute",
      "target_30d": 16858.06,
      "trend": "UP",
      "yhat": 16858.06,
      "yhat_lower": 16435.2,
      "yhat_upper": 17248.0,
      "train_start": "2023-06-01",
      "train_end": "2026-06-01",
      "train_rows": 709,
      "train_annualized_return": 0.4545
    },
    "FTSC_ci": {
      "ticker": "FTSC_ci",
      "last_price": 2340.0,
      "last_date": "2026-06-01",
      "signal": "VENTE FORTE",
      "confidence": "Basse",
      "target_30d": 1862.43,
      "trend": "DOWN",
      "yhat": 1862.43,
      "yhat_lower": 1502.98,
      "yhat_upper": 2214.1,
      "train_start": "2023-06-01",
      "train_end": "2026-06-01",
      "train_rows": 722,
      "train_annualized_return": 0.2597
    },
    "LNBB_bj": {
      "ticker": "LNBB_bj",
      "last_price": 3850.0,
      "last_date": "2026-06-01",
      "signal": "NEUTRE",
      "confidence": "Haute",
      "target_30d": 3903.53,
      "trend": "UP",
      "yhat": 3903.53,
      "yhat_lower": 3786.1,
      "yhat_upper": 4018.06,
      "train_start": "2024-12-13",
      "train_end": "2026-06-01",
      "train_rows": 334,
      "train_annualized_return": -0.1811
    },
    "NEIC_ci": {
      "ticker": "NEIC_ci",
      "last_price": 1990.0,
      "last_date": "2026-06-01",
      "signal": "ACHAT",
      "confidence": "Haute",
      "target_30d": 2078.58,
      "trend": "UP",
      "yhat": 2078.58,
      "yhat_lower": 2009.28,
      "yhat_upper": 2142.26,
      "train_start": "2023-06-15",
      "train_end": "2026-06-01",
      "train_rows": 579,
      "train_annualized_return": 0.4401
    },
    "NSBC_ci": {
      "ticker": "NSBC_ci",
      "last_price": 18000.0,
      "last_date": "2026-06-01",
      "signal": "VENTE",
      "confidence": "Haute",
      "target_30d": 16985.93,
      "trend": "DOWN",
      "yhat": 16985.93,
      "yhat_lower": 16544.01,
      "yhat_upper": 17460.14,
      "train_start": "2023-06-06",
      "train_end": "2026-06-01",
      "train_rows": 695,
      "train_annualized_return": 0.5059
    },
    "NTLC_ci": {
      "ticker": "NTLC_ci",
      "last_price": 12990.0,
      "last_date": "2026-06-01",
      "signal": "VENTE",
      "confidence": "Haute",
      "target_30d": 12557.28,
      "trend": "DOWN",
      "yhat": 12557.28,
      "yhat_lower": 12080.41,
      "yhat_upper": 13078.3,
      "train_start": "2023-06-14",
      "train_end": "2026-06-01",
      "train_rows": 648,
      "train_annualized_return": 0.193
    },
    "ONTBF_bf": {
      "ticker": "ONTBF_bf",
      "last_price": 2900.0,
      "last_date": "2026-06-01",
      "signal": "NEUTRE",
      "confidence": "Haute",
      "target_30d": 2907.87,
      "trend": "UP",
      "yhat": 2907.87,
      "yhat_lower": 2795.88,
      "yhat_upper": 3022.32,
      "train_start": "2023-06-01",
      "train_end": "2026-06-01",
      "train_rows": 724,
      "train_annualized_return": 0.0058
    },
    "ORAC_ci": {
      "ticker": "ORAC_ci",
      "last_price": 16000.0,
      "last_date": "2026-06-01",
      "signal": "NEUTRE",
      "confidence": "Haute",
      "target_30d": 15906.78,
      "trend": "DOWN",
      "yhat": 15906.78,
      "yhat_lower": 15431.9,
      "yhat_upper": 16361.37,
      "train_start": "2023-06-01",
      "train_end": "2026-06-01",
      "train_rows": 724,
      "train_annualized_return": 0.1865
    },
    "ORGT_tg": {
      "ticker": "ORGT_tg",
      "last_price": 2630.0,
      "last_date": "2026-06-01",
      "signal": "ACHAT FORT",
      "confidence": "Haute",
      "target_30d": 3376.73,
      "trend": "UP",
      "yhat": 3376.73,
      "yhat_lower": 3134.62,
      "yhat_upper": 3598.72,
      "train_start": "2023-06-01",
      "train_end": "2026-06-01",
      "train_rows": 663,
      "train_annualized_return": 0.0404
    },
    "PALC_ci": {
      "ticker": "PALC_ci",
      "last_price": 7975.0,
      "last_date": "2026-06-01",
      "signal": "NEUTRE",
      "confidence": "Haute",
      "target_30d": 8057.63,
      "trend": "UP",
      "yhat": 8057.63,
      "yhat_lower": 7694.31,
      "yhat_upper": 8414.52,
      "train_start": "2023-06-01",
      "train_end": "2026-06-01",
      "train_rows": 692,
      "train_annualized_return": -0.0663
    },
    "PRSC_ci": {
      "ticker": "PRSC_ci",
      "last_price": 4155.0,
      "last_date": "2026-06-01",
      "signal": "ACHAT FORT",
      "confidence": "Haute",
      "target_30d": 5141.08,
      "trend": "UP",
      "yhat": 5141.08,
      "yhat_lower": 4768.34,
      "yhat_upper": 5518.13,
      "train_start": "2023-06-01",
      "train_end": "2026-06-01",
      "train_rows": 668,
      "train_annualized_return": 0.1405
    },
    "SAFC_ci": {
      "ticker": "SAFC_ci",
      "last_price": 3595.0,
      "last_date": "2026-06-01",
      "signal": "ACHAT FORT",
      "confidence": "Moyenne",
      "target_30d": 5723.5,
      "trend": "UP",
      "yhat": 5723.5,
      "yhat_lower": 5150.44,
      "yhat_upper": 6273.37,
      "train_start": "2023-06-08",
      "train_end": "2026-06-01",
      "train_rows": 544,
      "train_annualized_return": 0.6411
    },
    "SCRC_ci": {
      "ticker": "SCRC_ci",
      "last_price": 2770.0,
      "last_date": "2026-06-01",
      "signal": "NEUTRE",
      "confidence": "Haute",
      "target_30d": 2710.24,
      "trend": "DOWN",
      "yhat": 2710.24,
      "yhat_lower": 2621.38,
      "yhat_upper": 2794.23,
      "train_start": "2023-06-01",
      "train_end": "2026-06-01",
      "train_rows": 678,
      "train_annualized_return": 0.669
    },
    "SDCC_ci": {
      "ticker": "SDCC_ci",
      "last_price": 11025.0,
      "last_date": "2026-06-01",
      "signal": "VENTE",
      "confidence": "Haute",
      "target_30d": 10332.08,
      "trend": "DOWN",
      "yhat": 10332.08,
      "yhat_lower": 10007.37,
      "yhat_upper": 10672.55,
      "train_start": "2023-06-02",
      "train_end": "2026-06-01",
      "train_rows": 714,
      "train_annualized_return": 0.3059
    },
    "SDSC_ci": {
      "ticker": "SDSC_ci",
      "last_price": 1880.0,
      "last_date": "2026-06-01",
      "signal": "VENTE",
      "confidence": "Haute",
      "target_30d": 1814.99,
      "trend": "DOWN",
      "yhat": 1814.99,
      "yhat_lower": 1699.37,
      "yhat_upper": 1935.52,
      "train_start": "2023-06-01",
      "train_end": "2026-06-01",
      "train_rows": 734,
      "train_annualized_return": 0.1166
    },
    "SEMC_ci": {
      "ticker": "SEMC_ci",
      "last_price": 1545.0,
      "last_date": "2026-06-01",
      "signal": "ACHAT FORT",
      "confidence": "Haute",
      "target_30d": 2338.09,
      "trend": "UP",
      "yhat": 2338.09,
      "yhat_lower": 2218.55,
      "yhat_upper": 2440.84,
      "train_start": "2026-01-02",
      "train_end": "2026-06-01",
      "train_rows": 107,
      "train_annualized_return": 4.8042
    },
    "SGBC_ci": {
      "ticker": "SGBC_ci",
      "last_price": 37000.0,
      "last_date": "2026-06-01",
      "signal": "ACHAT",
      "confidence": "Haute",
      "target_30d": 38664.24,
      "trend": "UP",
      "yhat": 38664.24,
      "yhat_lower": 37930.46,
      "yhat_upper": 39484.6,
      "train_start": "2023-06-01",
      "train_end": "2026-06-01",
      "train_rows": 715,
      "train_annualized_return": 0.3677
    },
    "SHEC_ci": {
      "ticker": "SHEC_ci",
      "last_price": 1915.0,
      "last_date": "2026-06-01",
      "signal": "ACHAT FORT",
      "confidence": "Haute",
      "target_30d": 2336.85,
      "trend": "UP",
      "yhat": 2336.85,
      "yhat_lower": 2246.67,
      "yhat_upper": 2421.02,
      "train_start": "2023-06-01",
      "train_end": "2026-06-01",
      "train_rows": 694,
      "train_annualized_return": 0.4405
    },
    "SIBC_ci": {
      "ticker": "SIBC_ci",
      "last_price": 8500.0,
      "last_date": "2026-06-01",
      "signal": "VENTE",
      "confidence": "Haute",
      "target_30d": 7952.94,
      "trend": "DOWN",
      "yhat": 7952.94,
      "yhat_lower": 7778.73,
      "yhat_upper": 8103.55,
      "train_start": "2023-06-01",
      "train_end": "2026-06-01",
      "train_rows": 736,
      "train_annualized_return": 0.4987
    },
    "SICC_ci": {
      "ticker": "SICC_ci",
      "last_price": 4270.0,
      "last_date": "2026-06-01",
      "signal": "NEUTRE",
      "confidence": "Moyenne",
      "target_30d": 4370.06,
      "trend": "UP",
      "yhat": 4370.06,
      "yhat_lower": 3990.53,
      "yhat_upper": 4759.0,
      "train_start": "2023-06-12",
      "train_end": "2026-06-01",
      "train_rows": 365,
      "train_annualized_return": -0.1005
    },
    "SIVC_ci": {
      "ticker": "SIVC_ci",
      "last_price": 2860.0,
      "last_date": "2026-06-01",
      "signal": "ACHAT FORT",
      "confidence": "Haute",
      "target_30d": 3489.9,
      "trend": "UP",
      "yhat": 3489.9,
      "yhat_lower": 3340.62,
      "yhat_upper": 3647.53,
      "train_start": "2023-06-01",
      "train_end": "2026-06-01",
      "train_rows": 568,
      "train_annualized_return": 0.6916
    },
    "SLBC_ci": {
      "ticker": "SLBC_ci",
      "last_price": 38000.0,
      "last_date": "2026-06-01",
      "signal": "ACHAT FORT",
      "confidence": "Haute",
      "target_30d": 46919.99,
      "trend": "UP",
      "yhat": 46919.99,
      "yhat_lower": 45034.85,
      "yhat_upper": 49037.07,
      "train_start": "2023-06-01",
      "train_end": "2026-06-01",
      "train_rows": 482,
      "train_annualized_return": 0.7316
    },
    "SMBC_ci": {
      "ticker": "SMBC_ci",
      "last_price": 13300.0,
      "last_date": "2026-06-01",
      "signal": "ACHAT",
      "confidence": "Haute",
      "target_30d": 14107.78,
      "trend": "UP",
      "yhat": 14107.78,
      "yhat_lower": 13379.55,
      "yhat_upper": 14802.63,
      "train_start": "2023-06-01",
      "train_end": "2026-06-01",
      "train_rows": 713,
      "train_annualized_return": 0.1942
    },
    "SNTS_sn": {
      "ticker": "SNTS_sn",
      "last_price": 28400.0,
      "last_date": "2026-06-01",
      "signal": "NEUTRE",
      "confidence": "Haute",
      "target_30d": 29021.56,
      "trend": "UP",
      "yhat": 29021.56,
      "yhat_lower": 28469.0,
      "yhat_upper": 29571.85,
      "train_start": "2023-06-01",
      "train_end": "2026-06-01",
      "train_rows": 655,
      "train_annualized_return": 0.2371
    },
    "SOGC_ci": {
      "ticker": "SOGC_ci",
      "last_price": 7490.0,
      "last_date": "2026-06-01",
      "signal": "ACHAT",
      "confidence": "Haute",
      "target_30d": 8061.15,
      "trend": "UP",
      "yhat": 8061.15,
      "yhat_lower": 7755.64,
      "yhat_upper": 8372.66,
      "train_start": "2023-06-01",
      "train_end": "2026-06-01",
      "train_rows": 737,
      "train_annualized_return": 0.1246
    },
    "SPHC_ci": {
      "ticker": "SPHC_ci",
      "last_price": 7100.0,
      "last_date": "2026-06-01",
      "signal": "ACHAT",
      "confidence": "Haute",
      "target_30d": 7653.39,
      "trend": "UP",
      "yhat": 7653.39,
      "yhat_lower": 7305.77,
      "yhat_upper": 7960.72,
      "train_start": "2023-06-01",
      "train_end": "2026-06-01",
      "train_rows": 711,
      "train_annualized_return": 0.2717
    },
    "STAC_ci": {
      "ticker": "STAC_ci",
      "last_price": 2815.0,
      "last_date": "2026-06-01",
      "signal": "ACHAT FORT",
      "confidence": "Haute",
      "target_30d": 3455.14,
      "trend": "UP",
      "yhat": 3455.14,
      "yhat_lower": 3279.18,
      "yhat_upper": 3624.03,
      "train_start": "2023-06-07",
      "train_end": "2026-06-01",
      "train_rows": 588,
      "train_annualized_return": 0.3515
    },
    "STBC_ci": {
      "ticker": "STBC_ci",
      "last_price": 21300.0,
      "last_date": "2026-06-01",
      "signal": "ACHAT",
      "confidence": "Haute",
      "target_30d": 22215.55,
      "trend": "UP",
      "yhat": 22215.55,
      "yhat_lower": 21431.98,
      "yhat_upper": 23011.76,
      "train_start": "2023-06-01",
      "train_end": "2026-06-01",
      "train_rows": 630,
      "train_annualized_return": 0.4925
    },
    "TTLC_ci": {
      "ticker": "TTLC_ci",
      "last_price": 2850.0,
      "last_date": "2026-06-01",
      "signal": "NEUTRE",
      "confidence": "Haute",
      "target_30d": 2854.54,
      "trend": "UP",
      "yhat": 2854.54,
      "yhat_lower": 2658.7,
      "yhat_upper": 3078.24,
      "train_start": "2023-06-01",
      "train_end": "2026-06-01",
      "train_rows": 730,
      "train_annualized_return": 0.1079
    },
    "TTLS_sn": {
      "ticker": "TTLS_sn",
      "last_price": 3365.0,
      "last_date": "2026-06-01",
      "signal": "ACHAT",
      "confidence": "Haute",
      "target_30d": 3524.23,
      "trend": "UP",
      "yhat": 3524.23,
      "yhat_lower": 3397.9,
      "yhat_upper": 3639.93,
      "train_start": "2023-06-01",
      "train_end": "2026-06-01",
      "train_rows": 721,
      "train_annualized_return": 0.0918
    },
    "UNLC_ci": {
      "ticker": "UNLC_ci",
      "last_price": 57100.0,
      "last_date": "2026-06-01",
      "signal": "ACHAT FORT",
      "confidence": "Moyenne",
      "target_30d": 69125.95,
      "trend": "UP",
      "yhat": 69125.95,
      "yhat_lower": 63153.61,
      "yhat_upper": 75735.71,
      "train_start": "2023-06-01",
      "train_end": "2026-06-01",
      "train_rows": 306,
      "train_annualized_return": 1.0474
    },
    "UNXC_ci": {
      "ticker": "UNXC_ci",
      "last_price": 1780.0,
      "last_date": "2026-06-01",
      "signal": "ACHAT FORT",
      "confidence": "Haute",
      "target_30d": 2128.03,
      "trend": "UP",
      "yhat": 2128.03,
      "yhat_lower": 2006.68,
      "yhat_upper": 2261.04,
      "train_start": "2023-06-01",
      "train_end": "2026-06-01",
      "train_rows": 703,
      "train_annualized_return": 0.4208
    }
  }
}